pytest_repeater/__init__.py
pytest_repeater/plugin.py
pytest_repeater-0.1.0.dist-info/top_level.txt
pytest_repeater-0.1.0.dist-info/entry_points.txt
pytest_repeater-0.1.0.dist-info/METADATA
pytest_repeater-0.1.0.dist-info/DESCRIPTION.rst
pytest_repeater-0.1.0.dist-info/metadata.json
pytest_repeater-0.1.0.dist-info/WHEEL
pytest_repeater-0.1.0.dist-info/RECORD
