Metadata-Version: 2.0
Name: pytest-repeater
Version: 0.1.0
Summary: py.test plugin for repeating single test multiple times.
Home-page: https://github.com/ClearcodeHQ/pytest-repeater
Author: The A Room
Author-email: thearoom@clearcode.cc
License: GNU Lesser General Public License v3 (LGPLv3)
Keywords: python py.test
Platform: UNKNOWN
Classifier: Development Status :: 1 - Planning
Classifier: Intended Audience :: Developers
Classifier: License :: OSI Approved :: GNU Lesser General Public License v3 (LGPLv3)
Classifier: Natural Language :: English
Classifier: Operating System :: OS Independent
Classifier: Programming Language :: Python
Classifier: Programming Language :: Python :: 2.7
Classifier: Programming Language :: Python :: 3
Classifier: Topic :: Software Development :: Libraries :: Python Modules
Classifier: Topic :: Software Development :: Testing
Provides-Extra: tests
Requires-Dist: pytest; extra == 'tests'
Requires-Dist: pytest-cov; extra == 'tests'
Requires-Dist: pylama; extra == 'tests'
